Flask_Wallet_RPC-0.1.5.dist-info/METADATA
Flask_Wallet_RPC-0.1.5.dist-info/RECORD
Flask_Wallet_RPC-0.1.5.dist-info/WHEEL
Flask_Wallet_RPC-0.1.5.dist-info/top_level.txt
flask_wallet_rpc/__init__.py
flask_wallet_rpc/wallet_rpc.py
